double_indent.py
double_indent_rotki-0.1.7.dist-info/LICENCE
double_indent_rotki-0.1.7.dist-info/METADATA
double_indent_rotki-0.1.7.dist-info/WHEEL
double_indent_rotki-0.1.7.dist-info/entry_points.txt
double_indent_rotki-0.1.7.dist-info/top_level.txt
double_indent_rotki-0.1.7.dist-info/RECORD
