Metadata-Version: 2.1
Name: double-indent-rotki
Version: 0.1.7
Summary: a code formatter indenting function and method definitions twice. Fork to accept directories and more.
Home-page: https://github.com/LefterisJP/double-indent
Author: Lefteris Karapetsas
Author-email: lefteris@refu.co
License: MIT
Classifier: License :: OSI Approved :: MIT License
Classifier: Programming Language :: Python :: 3
Classifier: Programming Language :: Python :: 3 :: Only
Classifier: Programming Language :: Python :: Implementation :: CPython
Requires-Python: >=3.8
License-File: LICENCE
Requires-Dist: tokenize-rt
